arnelify-orm-ffi.cpython-311-x86_64-linux-gnu.so
arnelify_orm/__init__.py
arnelify_orm/mysql/__init__.py
arnelify_orm/mysql/index.py
arnelify_orm/mysql/query/__init__.py
arnelify_orm/mysql/query/index.py
arnelify_orm-0.7.5.dist-info/licenses/LICENSE
arnelify_orm-0.7.5.dist-info/METADATA
arnelify_orm-0.7.5.dist-info/WHEEL
arnelify_orm-0.7.5.dist-info/top_level.txt
arnelify_orm-0.7.5.dist-info/RECORD
