Metadata-Version: 2.4
Name: arnelify_orm
Version: 0.7.5
Summary: Minimalistic dynamic library which is an ORM written in C and C++.
Home-page: https://github.com/arnelify/arnelify-orm-python
Author: Arnelify
License: MIT
Keywords: arnelify arnelify-orm-python arnelify-orm
Classifier: Programming Language :: Python :: 3
License-File: LICENSE
Requires-Dist: cffi
Requires-Dist: setuptools
Requires-Dist: wheel
Dynamic: author
Dynamic: classifier
Dynamic: description
Dynamic: description-content-type
Dynamic: home-page
Dynamic: keywords
Dynamic: license
Dynamic: license-file
Dynamic: requires-dist
Dynamic: summary
